{"cameraMode":{"drawMode":0,"name":"Shaded","section":"Shading Mode"},"sceneLighting":true,"audioPlay":false,"sceneViewState":{"showFog":true,"showMaterialUpdate":false,"showSkybox":true,"showFlares":true,"showImageEffects":true,"showParticleSystems":true},"in2DMode":false,"pivot":{"x":393.3421325683594,"y":338.9928283691406,"z":6.406064987182617},"rotation":{"x":0.04049734026193619,"y":0.012645029462873936,"z":-0.0004869319382123649,"w":0.9991214275360107},"size":952.6076049804688,"orthographic":false}